fairxplainer/__init__.py
fairxplainer/backfitting.py
fairxplainer/fair_explainer.py
fairxplainer/hdmr.py
fairxplainer/utils.py
fairxplainer/salib_util/__init__.py
fairxplainer/salib_util/results.py
fairxplainer/wrapper/__init__.py
fairxplainer/wrapper/decision_tree_wrap.py
fairxplainer/wrapper/linear_classifier_wrap.py
fairxplainer/wrapper/mlp_wrap.py
fairxplainer/wrapper/shap_fairness_explanation.py
fairxplainer-0.4.0.dist-info/LICENSE
fairxplainer-0.4.0.dist-info/METADATA
fairxplainer-0.4.0.dist-info/WHEEL
fairxplainer-0.4.0.dist-info/top_level.txt
fairxplainer-0.4.0.dist-info/RECORD
