Metadata-Version: 2.1
Name: fairxplainer
Version: 0.4.0
Summary: A Python package for explaining bias in machine learning models
Home-page: https://github.com/ReAILe/bias-explainer
Author: Bishwamittra Ghosh
Author-email: bishwamittra.ghosh@gmail.com
License: MIT
Keywords: Fair Machine Learning,Bias,Explainability,Global Sensitivity Analysis,Variance Decomposition,Influence Functions
Classifier: Development Status :: 3 - Alpha
Classifier: Intended Audience :: Developers
Classifier: Topic :: Software Development :: Build Tools
Classifier: License :: OSI Approved :: MIT License
Classifier: Programming Language :: Python :: 3.7
License-File: LICENSE
